croppicDjango/__init__.py
croppicDjango/admin.py
croppicDjango/conf.py
croppicDjango/forms.py
croppicDjango/models.py
croppicDjango/tests.py
croppicDjango/urls.py
croppicDjango/utils.py
croppicDjango/views.py
croppicDjango/migrations/__init__.py
croppicDjango-0.0.2.dist-info/METADATA
croppicDjango-0.0.2.dist-info/RECORD
croppicDjango-0.0.2.dist-info/WHEEL
croppicDjango-0.0.2.dist-info/top_level.txt
